Workbook
Name Slicer_COFFEE_TYPE: #N/A
Name Slicer_COUNTRY: #N/A
Name Slicer_YEAR: #N/A

Sheet Orders
A1: Order ID | B1: Order Date | C1: Customer ID | D1: Product ID | E1: Quantity | F1: Size | G1: Unit Price | H1: Sales
A2: QEV-37451-860 | B2: 43713 | C2: 17670-51384-MA | D2: R-M-1 | E2: 2 | F2: =INDEX([1]products!$A$1:$G$49,MATCH([1]orders!$D2,[1]products!$A$1:$A$49,0),MATCH([1]orders!K$1,[1]products!$A$1:$G$1,0)) -> 1 | G2: =INDEX([1]products!$A$1:$G$49,MATCH([1]orders!$D2,[1]products!$A$1:$A$49,0),MATCH([1]orders!L$1,[1]products!$A$1:$G$1,0)) -> 9.95 | H2: =E2*G2 -> 19.9
A3: QEV-37451-860 | B3: 43713 | C3: 17670-51384-MA | D3: E-M-0.5 | E3: 5 | F3: =INDEX([1]products!$A$1:$G$49,MATCH([1]orders!$D3,[1]products!$A$1:$A$49,0),MATCH([1]orders!K$1,[1]products!$A$1:$G$1,0)) -> 0.5 | G3: =INDEX([1]products!$A$1:$G$49,MATCH([1]orders!$D3,[1]products!$A$1:$A$49,0),MATCH([1]orders!L$1,[1]products!$A$1:$G$1,0)) -> 8.25 | H3: =E3*G3 -> 41.25
A4: FAA-43335-268 | B4: 44364 | C4: 21125-22134-PX | D4: A-L-1 | E4: 1 | F4: =INDEX([1]products!$A$1:$G$49,MATCH([1]orders!$D4,[1]products!$A$1:$A$49,0),MATCH([1]orders!K$1,[1]products!$A$1:$G$1,0)) -> 1 | G4: =INDEX([1]products!$A$1:$G$49,MATCH([1]orders!$D4,[1]products!$A$1:$A$49,0),MATCH([1]orders!L$1,[1]products!$A$1:$G$1,0)) -> 12.95 | H4: =E4*G4 -> 12.95
A5: KAC-83089-793 | B5: 44392 | C5: 23806-46781-OU | D5: E-M-1 | E5: 2 | F5: =INDEX([1]products!$A$1:$G$49,MATCH([1]orders!$D5,[1]products!$A$1:$A$49,0),MATCH([1]orders!K$1,[1]products!$A$1:$G$1,0)) -> 1 | G5: =INDEX([1]products!$A$1:$G$49,MATCH([1]orders!$D5,[1]products!$A$1:$A$49,0),MATCH([1]orders!L$1,[1]products!$A$1:$G$1,0)) -> 13.75 | H5: =E5*G5 -> 27.5
A6: KAC-83089-793 | B6: 44392 | C6: 23806-46781-OU | D6: R-L-2.5 | E6: 2 | F6: =INDEX([1]products!$A$1:$G$49,MATCH([1]orders!$D6,[1]products!$A$1:$A$49,0),MATCH([1]orders!K$1,[1]products!$A$1:$G$1,0)) -> 2.5 | G6: =INDEX([1]products!$A$1:$G$49,MATCH([1]orders!$D6,[1]products!$A$1:$A$49,0),MATCH([1]orders!L$1,[1]products!$A$1:$G$1,0)) -> 27.485 | H6: =E6*G6 -> 54.97
A7: CVP-18956-553 | B7: 44412 | C7: 86561-91660-RB | D7: L-D-1 | E7: 3 | F7: =INDEX([1]products!$A$1:$G$49,MATCH([1]orders!$D7,[1]products!$A$1:$A$49,0),MATCH([1]orders!K$1,[1]products!$A$1:$G$1,0)) -> 1 | G7: =INDEX([1]products!$A$1:$G$49,MATCH([1]orders!$D7,[1]products!$A$1:$A$49,0),MATCH([1]orders!L$1,[1]products!$A$1:$G$1,0)) -> 12.95 | H7: =E7*G7 -> 38.85
A8: IPP-31994-879 | B8: 44582 | C8: 65223-29612-CB | D8: E-D-0.5 | E8: 3 | F8: =INDEX([1]products!$A$1:$G$49,MATCH([1]orders!$D8,[1]products!$A$1:$A$49,0),MATCH([1]orders!K$1,[1]products!$A$1:$G$1,0)) -> 0.5 | G8: =INDEX([1]products!$A$1:$G$49,MATCH([1]orders!$D8,[1]products!$A$1:$A$49,0),MATCH([1]orders!L$1,[1]products!$A$1:$G$1,0)) -> 7.29 | H8: =E8*G8 -> 21.87
A9: SNZ-65340-705 | B9: 44701 | C9: 21134-81676-FR | D9: L-L-0.2 | E9: 1 | F9: =INDEX([1]products!$A$1:$G$49,MATCH([1]orders!$D9,[1]products!$A$1:$A$49,0),MATCH([1]orders!K$1,[1]products!$A$1:$G$1,0)) -> 0.2 | G9: =INDEX([1]products!$A$1:$G$49,MATCH([1]orders!$D9,[1]products!$A$1:$A$49,0),MATCH([1]orders!L$1,[1]products!$A$1:$G$1,0)) -> 4.755 | H9: =E9*G9 -> 4.755
A10: EZT-46571-659 | B10: 43467 | C10: 03396-68805-ZC | D10: R-M-0.5 | E10: 3 | F10: =INDEX([1]products!$A$1:$G$49,MATCH([1]orders!$D10,[1]products!$A$1:$A$49,0),MATCH([1]orders!K$1,[1]products!$A$1:$G$1,0)) -> 0.5 | G10: =INDEX([1]products!$A$1:$G$49,MATCH([1]orders!$D10,[1]products!$A$1:$A$49,0),MATCH([1]orders!L$1,[1]products!$A$1:$G$1,0)) -> 5.97 | H10: =E10*G10 -> 17.91
A11: NWQ-70061-912 | B11: 43713 | C11: 61021-27840-ZN | D11: R-M-0.5 | E11: 1 | F11: =INDEX([1]products!$A$1:$G$49,MATCH([1]orders!$D11,[1]products!$A$1:$A$49,0),MATCH([1]orders!K$1,[1]products!$A$1:$G$1,0)) -> 0.5 | G11: =INDEX([1]products!$A$1:$G$49,MATCH([1]orders!$D11,[1]products!$A$1:$A$49,0),MATCH([1]orders!L$1,[1]products!$A$1:$G$1,0)) -> 5.97 | H11: =E11*G11 -> 5.97
A12: BKK-47233-845 | B12: 44263 | C12: 76239-90137-UQ | D12: A-D-1 | E12: 4 | F12: =INDEX([1]products!$A$1:$G$49,MATCH([1]orders!$D12,[1]products!$A$1:$A$49,0),MATCH([1]orders!K$1,[1]products!$A$1:$G$1,0)) -> 1 | G12: =INDEX([1]products!$A$1:$G$49,MATCH([1]orders!$D12,[1]products!$A$1:$A$49,0),MATCH([1]orders!L$1,[1]products!$A$1:$G$1,0)) -> 9.95 | H12: =E12*G12 -> 39.8
A13: VQR-01002-970 | B13: 44132 | C13: 49315-21985-BB | D13: E-L-2.5 | E13: 5 | F13: =INDEX([1]products!$A$1:$G$49,MATCH([1]orders!$D13,[1]products!$A$1:$A$49,0),MATCH([1]orders!K$1,[1]products!$A$1:$G$1,0)) -> 2.5 | G13: =INDEX([1]products!$A$1:$G$49,MATCH([1]orders!$D13,[1]products!$A$1:$A$49,0),MATCH([1]orders!L$1,[1]products!$A$1:$G$1,0)) -> 34.155 | H13: =E13*G13 -> 170.775
... A1001: IRV-20769-219 | B1001: 44119 | C1001: 77131-58092-GE | D1001: E-M-0.2 | E1001: 3 | F1001: =INDEX([1]products!$A$1:$G$49,MATCH([1]orders!$D1001,[1]products!$A$1:$A$49,0),MATCH([1]orders!K$1,[1]products!$A$1:$G$1,0)) -> 0.2 | G1001: =INDEX([1]products!$A$1:$G$49,MATCH([1]orders!$D1001,[1]products!$A$1:$A$49,0),MATCH([1]orders!L$1,[1]products!$A$1:$G$1,0)) -> 4.125 | H1001: =E1001*G1001 -> 12.375

Sheet Customers
A1: Customer ID | B1: Customer Name | C1: Email | D1: Phone Number | E1: Address Line 1 | F1: City | G1: Country | H1: Postcode | I1: Loyalty Card
A2: 17670-51384-MA | B2: Aloisia Allner | C2: aallner0@lulu.com | D2: +1 (862) 817-0124 | E2: 57999 Pepper Wood Alley | F2: Paterson | G2: United States | H2: 7505 | I2: Yes
A3: 73342-18763-UW | B3: Piotr Bote | C3: pbote1@yelp.com | D3: +353 (913) 396-4653 | E3: 2112 Ridgeway Hill | F3: Crumlin | G3: Ireland | H3: D6W | I3: No
A4: 21125-22134-PX | B4: Jami Redholes | C4: jredholes2@tmall.com | D4: +1 (210) 986-6806 | E4: 5214 Bartillon Park | F4: San Antonio | G4: United States | H4: 78205 | I4: Yes
A5: 71253-00052-RN | B5: Dene Azema | C5: dazema3@facebook.com | D5: +1 (217) 418-0714 | E5: 27 Maywood Place | F5: Springfield | G5: United States | H5: 62711 | I5: Yes
A6: 23806-46781-OU | B6: Christoffer O' Shea | D6: +353 (698) 362-9201 | E6: 38980 Manitowish Junction | F6: Cill Airne | G6: Ireland | H6: N41 | I6: No
A7: 86561-91660-RB | B7: Beryle Cottier | D7: +1 (570) 289-7473 | E7: 2651 Stoughton Place | F7: Scranton | G7: United States | H7: 18505 | I7: No
A8: 65223-29612-CB | B8: Shaylynn Lobe | C8: slobe6@nifty.com | D8: +1 (937) 954-4541 | E8: 7005 Mariners Cove Place | F8: Dayton | G8: United States | H8: 45440 | I8: Yes
A9: 21134-81676-FR | B9: Melvin Wharfe | D9: +353 (507) 574-3034 | E9: 7 Straubel Road | F9: Kill | G9: Ireland | H9: P24 | I9: Yes
A10: 03396-68805-ZC | B10: Guthrey Petracci | C10: gpetracci8@livejournal.com | D10: +1 (310) 868-1842 | E10: 949 Paget Parkway | F10: Los Angeles | G10: United States | H10: 90045 | I10: No
A11: 61021-27840-ZN | B11: Rodger Raven | C11: rraven9@ed.gov | D11: +1 (213) 263-0288 | E11: 1 Reinke Avenue | F11: Los Angeles | G11: United States | H11: 90065 | I11: No
A12: 76239-90137-UQ | B12: Ferrell Ferber | C12: fferbera@businesswire.com | D12: +1 (408) 383-5302 | E12: 68 High Crossing Court | F12: San Jose | G12: United States | H12: 95160 | I12: No
A13: 49315-21985-BB | B13: Duky Phizackerly | C13: dphizackerlyb@utexas.edu | D13: +1 (408) 533-6012 | E13: 28643 Bluejay Crossing | F13: San Jose | G13: United States | H13: 95194 | I13: Yes
A14: 34136-36674-OM | B14: Rosaleen Scholar | C14: rscholarc@nyu.edu | D14: +1 (804) 420-0420 | E14: 80915 Montana Park | F14: Richmond | G14: United States | H14: 23285 | I14: No
A15: 39396-12890-PE | B15: Terence Vanyutin | C15: tvanyutind@wix.com | E15: 331 Bunting Hill | F15: Migrate | G15: United States | H15: 41905 | I15: No
A16: 95875-73336-RG | B16: Patrice Trobe | C16: ptrobee@wunderground.com | D16: +1 (314) 240-7896 | E16: 827 Declaration Plaza | F16: Saint Louis | G16: United States | H16: 63131 | I16: Yes
A17: 25473-43727-BY | B17: Llywellyn Oscroft | C17: loscroftf@ebay.co.uk | E17: 022 Roth Place | F17: Philadelphia | G17: United States | H17: 19172 | I17: No
A18: 99643-51048-IQ | B18: Minni Alabaster | C18: malabasterg@hexun.com | D18: +1 (971) 483-6255 | E18: 3 Charing Cross Trail | F18: Portland | G18: United States | H18: 97271 | I18: No
A19: 62173-15287-CU | B19: Rhianon Broxup | C19: rbroxuph@jimdo.com | D19: +1 (713) 663-1338 | E19: 83517 Thierer Court | F19: Houston | G19: United States | H19: 77240 | I19: No
A20: 57611-05522-ST | B20: Pall Redford | C20: predfordi@ow.ly | E20: 7337 Hayes Junction | F20: Caherconlish | G20: Ireland | H20: F45 | I20: Yes
A21: 76664-37050-DT | B21: Aurea Corradino | C21: acorradinoj@harvard.edu | D21: +1 (646) 202-5965 | E21: 698 Canary Terrace | F21: New York City | G21: United States | H21: 10060 | I21: Yes
A22: 84565-53984-SX | B22: Kendal Scardefield | D22: +353 (733) 405-3302 | E22: 3 Northridge Crossing | F22: Clondalkin | G22: Ireland | H22: D24 | I22: Yes
A23: 03090-88267-BQ | B23: Avrit Davidowsky | C23: adavidowskyl@netvibes.com | D23: +1 (616) 481-9962 | E23: 9 Warrior Junction | F23: Grand Rapids | G23: United States | H23: 49560 | I23: No
A24: 37651-47492-NC | B24: Annabel Antuk | C24: aantukm@kickstarter.com | D24: +1 (941) 740-6268 | E24: 77965 Lawn Park | F24: Punta Gorda | G24: United States | H24: 33982 | I24: Yes
A25: 95399-57205-HI | B25: Iorgo Kleinert | C25: ikleinertn@timesonline.co.uk | D25: +1 (360) 352-6598 | E25: 1 Morningstar Lane | F25: Vancouver | G25: United States | H25: 98682 | I25: Yes
A26: 24010-66714-HW | B26: Chrisy Blofeld | C26: cblofeldo@amazon.co.uk | D26: +1 (303) 936-3357 | E26: 013 Talisman Terrace | F26: Englewood | G26: United States | H26: 80150 | I26: No
A27: 07591-92789-UA | B27: Culley Farris | D27: +1 (941) 267-4822 | E27: 4 Mitchell Drive | F27: Punta Gorda | G27: United States | H27: 33982 | I27: Yes
A28: 49231-44455-IC | B28: Selene Shales | C28: sshalesq@umich.edu | D28: +1 (707) 881-5004 | E28: 74 Bultman Plaza | F28: Petaluma | G28: United States | H28: 94975 | I28: Yes
A29: 50124-88608-EO | B29: Vivie Danneil | C29: vdanneilr@mtv.com | D29: +353 (751) 346-0399 | E29: 5626 Darwin Avenue | F29: Tralee | G29: Ireland | H29: V92 | I29: No
A30: 00888-74814-UZ | B30: Theresita Newbury | C30: tnewburys@usda.gov | D30: +353 (803) 587-0026 | E30: 79526 Bultman Lane | F30: Clonskeagh | G30: Ireland | H30: D04 | I30: No
A31: 14158-30713-OB | B31: Mozelle Calcutt | C31: mcalcuttt@baidu.com | D31: +353 (928) 869-1762 | E31: 4389 Russell Way | F31: Rathwire | G31: Ireland | H31: Y25 | I31: Yes
A32: 51427-89175-QJ | B32: Adrian Swaine | D32: +1 (303) 486-9517 | E32: 95 Straubel Hill | F32: Aurora | G32: United States | H32: 80044 | I32: No
A33: 52082-49024-ON | B33: Ray Leivesley | C33: rleivesleyv@canalblog.com | D33: +1 (212) 535-7791 | E33: 91 Stephen Drive | F33: Jamaica | G33: United States | H33: 11407 | I33: No
A34: 04540-43685-DV | B34: Nelly Basezzi | C34: nbasezziw@webeden.co.uk | D34: +353 (125) 815-7345 | E34: 923 Mallard Junction | F34: Bailieborough | G34: Ireland | H34: C15 | I34: Yes
A35: 39123-12846-YJ | B35: Gallard Gatheral | C35: ggatheralx@123-reg.co.uk | E35: 40 Clemons Place | F35: Grand Forks | G35: United States | H35: 58207 | I35: No
A36: 44981-99666-XB | B36: Una Welberry | C36: uwelberryy@ebay.co.uk | D36: +44 (392) 503-8132 | E36: 40915 Schlimgen Park | F36: Upton | G36: United Kingdom | H36: DN21 | I36: Yes
A37: 24825-51803-CQ | B37: Faber Eilhart | C37: feilhartz@who.int | D37: +1 (304) 510-6095 | E37: 6966 Victoria Street | F37: Charleston | G37: United States | H37: 25362 | I37: No
A38: 77634-13918-GJ | B38: Zorina Ponting | C38: zponting10@altervista.org | D38: +1 (501) 172-1476 | E38: 7118 Holmberg Court | F38: Little Rock | G38: United States | H38: 72204 | I38: No
A39: 13694-25001-LX | B39: Silvio Strase | C39: sstrase11@booking.com | D39: +1 (303) 579-8015 | E39: 5 Forest Lane | F39: Denver | G39: United States | H39: 80291 | I39: No
A40: 08523-01791-TI | B40: Dorie de la Tremoille | C40: dde12@unesco.org | D40: +1 (612) 492-5160 | E40: 0817 Dennis Street | F40: Minneapolis | G40: United States | H40: 55458 | I40: No
A41: 49860-68865-AB | B41: Hy Zanetto | E41: 469 Paget Place | F41: Tucson | G41: United States | H41: 85715 | I41: Yes
A42: 21240-83132-SP | B42: Jessica McNess | D42: +1 (504) 545-1478 | E42: 664 Erie Place | F42: New Orleans | G42: United States | H42: 70116 | I42: No
A43: 08350-81623-TF | B43: Lorenzo Yeoland | C43: lyeoland15@pbs.org | D43: +1 (860) 576-2887 | E43: 8510 Merrick Road | F43: Hartford | G43: United States | H43: 6183 | I43: Yes
A44: 73284-01385-SJ | B44: Abigail Tolworthy | C44: atolworthy16@toplist.cz | D44: +1 (801) 722-4425 | E44: 74 Shopko Way | F44: Ogden | G44: United States | H44: 84409 | I44: Yes
A45: 04152-34436-IE | B45: Maurie Bartol | D45: +1 (617) 493-7594 | E45: 7625 Starling Court | F45: Boston | G45: United States | H45: 2216 | I45: No
A46: 06631-86965-XP | B46: Olag Baudassi | C46: obaudassi18@seesaa.net | D46: +1 (585) 356-6251 | E46: 55 Dottie Court | F46: Rochester | G46: United States | H46: 14604 | I46: Yes
A47: 54619-08558-ZU | B47: Petey Kingsbury | C47: pkingsbury19@comcast.net | D47: +1 (917) 705-8224 | E47: 28 Loftsgordon Place | F47: Bronx | G47: United States | H47: 10469 | I47: No
A48: 85589-17020-CX | B48: Donna Baskeyfied | D48: +1 (205) 923-1460 | E48: 7586 Logan Avenue | F48: Birmingham | G48: United States | H48: 35205 | I48: Yes
A49: 36078-91009-WU | B49: Arda Curley | C49: acurley1b@hao123.com | D49: +1 (760) 840-3808 | E49: 45098 Scott Drive | F49: San Bernardino | G49: United States | H49: 92415 | I49: Yes
A50: 15770-27099-GX | B50: Raynor McGilvary | C50: rmcgilvary1c@tamu.edu | E50: 496 Rockefeller Court | F50: Norfolk | G50: United States | H50: 23514 | I50: No
A51: 91460-04823-BX | B51: Isis Pikett | C51: ipikett1d@xinhuanet.com | D51: +1 (202) 871-9039 | E51: 5892 Hauk Drive | F51: Washington | G51: United States | H51: 20409 | I51: No
A52: 45089-52817-WN | B52: Inger Bouldon | C52: ibouldon1e@gizmodo.com | D52: +1 (754) 391-4736 | E52: 925 Barby Circle | F52: Fort Lauderdale | G52: United States | H52: 33355 | I52: No
A53: 76447-50326-IC | B53: Karry Flanders | C53: kflanders1f@over-blog.com | D53: +353 (467) 720-7274 | E53: 88 Blue Bill Park Avenue | F53: Crumlin | G53: Ireland | H53: D6W | I53: Yes
A54: 26333-67911-OL | B54: Hartley Mattioli | C54: hmattioli1g@webmd.com | E54: 126 Valley Edge Street | F54: Kinloch | G54: United Kingdom | H54: PH43 | I54: No
A55: 40768-49176-BL | B55: Horatio Rubberts | C55: hrubberts1h@google.com.hk | D55: +1 (801) 635-8791 | E55: 459 Russell Center | F55: Provo | G55: United States | H55: 84605 | I55: No
A56: 22107-86640-SB | B56: Archambault Gillard | C56: agillard1i@issuu.com | D56: +1 (419) 663-2236 | E56: 97490 Susan Avenue | F56: Toledo | G56: United States | H56: 43666 | I56: No
A57: 09960-34242-LZ | B57: Salomo Cushworth | D57: +1 (609) 409-7044 | E57: 44 Oneill Parkway | F57: Trenton | G57: United States | H57: 8650 | I57: No
A58: 04671-85591-RT | B58: Theda Grizard | C58: tgrizard1k@odnoklassniki.ru | D58: +1 (813) 243-2150 | E58: 6 Knutson Pass | F58: Tampa | G58: United States | H58: 33686 | I58: Yes
A59: 25729-68859-UA | B59: Rozele Relton | C59: rrelton1l@stanford.edu | D59: +1 (850) 626-1181 | E59: 2484 Reindahl Court | F59: Pensacola | G59: United States | H59: 32590 | I59: No
A60: 05501-86351-NX | B60: Willa Rolling | D60: +1 (813) 759-3534 | E60: 3 Mockingbird Plaza | F60: Zephyrhills | G60: United States | H60: 33543 | I60: Yes
A61: 04521-04300-OK | B61: Stanislaus Gilroy | C61: sgilroy1n@eepurl.com | E61: 9120 Harbort Terrace | F61: Saint Paul | G61: United States | H61: 55123 | I61: Yes
A62: 58689-55264-VK | B62: Correy Cottingham | C62: ccottingham1o@wikipedia.org | D62: +1 (260) 764-1820 | E62: 394 Logan Road | F62: Fort Wayne | G62: United States | H62: 46862 | I62: No
A63: 79436-73011-MM | B63: Pammi Endacott | D63: +44 (177) 260-5076 | E63: 5841 Atwood Lane | F63: Wootton | G63: United Kingdom | H63: NN4 | I63: Yes
A64: 65552-60476-KY | B64: Nona Linklater | D64: +1 (239) 347-9766 | E64: 856 Bonner Parkway | F64: Naples | G64: United States | H64: 34114 | I64: Yes
A65: 69904-02729-YS | B65: Annadiane Dykes | C65: adykes1r@eventbrite.com | D65: +1 (312) 111-6203 | E65: 31 Northport Terrace | F65: Chicago | G65: United States | H65: 60681 | I65: No
A66: 01433-04270-AX | B66: Felecia Dodgson | D66: +1 (973) 434-8662 | E66: 48053 8th Crossing | F66: Newark | G66: United States | H66: 7104 | I66: Yes
A67: 14204-14186-LA | B67: Angelia Cockrem | C67: acockrem1t@engadget.com | D67: +1 (571) 316-8217 | E67: 1 Sherman Alley | F67: Vienna | G67: United States | H67: 22184 | I67: Yes
A68: 32948-34398-HC | B68: Belvia Umpleby | C68: bumpleby1u@soundcloud.com | D68: +1 (682) 627-0888 | E68: 710 Prairie Rose Terrace | F68: Fort Worth | G68: United States | H68: 76178 | I68: Yes
A69: 77343-52608-FF | B69: Nat Saleway | C69: nsaleway1v@dedecms.com | D69: +1 (323) 473-0294 | E69: 0780 Anthes Plaza | F69: Burbank | G69: United States | H69: 91505 | I69: No
A70: 42770-36274-QA | B70: Hayward Goulter | C70: hgoulter1w@abc.net.au | D70: +1 (423) 764-7751 | E70: 2081 Mariners Cove Drive | F70: Kingsport | G70: United States | H70: 37665 | I70: No
A71: 14103-58987-ZU | B71: Gay Rizzello | C71: grizzello1x@symantec.com | D71: +44 (247) 225-8003 | E71: 21 Schmedeman Crossing | F71: Liverpool | G71: United Kingdom | H71: L33 | I71: Yes
A72: 69958-32065-SW | B72: Shannon List | C72: slist1y@mapquest.com | D72: +1 (614) 279-9816 | E72: 7123 Algoma Center | F72: Columbus | G72: United States | H72: 43231 | I72: No
A73: 69533-84907-FA | B73: Shirlene Edmondson | C73: sedmondson1z@theguardian.com | D73: +353 (248) 428-7978 | E73: 4752 International Point | F73: Newmarket on Fergus | G73: Ireland | H73: P17 | I73: No
A74: 76005-95461-CI | B74: Aurlie McCarl | D74: +1 (504) 209-2724 | E74: 731 David Park | F74: New Orleans | G74: United States | H74: 70183 | I74: No
A75: 15395-90855-VB | B75: Alikee Carryer | D75: +1 (704) 799-5219 | E75: 247 Helena Drive | F75: Charlotte | G75: United States | H75: 28230 | I75: Yes
A76: 80640-45811-LB | B76: Jennifer Rangall | C76: jrangall22@newsvine.com | D76: +1 (781) 512-6637 | E76: 0 Grasskamp Lane | F76: Springfield | G76: United States | H76: 1114 | I76: Yes
A77: 28476-04082-GR | B77: Kipper Boorn | C77: kboorn23@ezinearticles.com | D77: +353 (359) 134-1550 | E77: 9513 Meadow Ridge Parkway | F77: Listowel | G77: Ireland | H77: V31 | I77: Yes
A78: 12018-75670-EU | B78: Melania Beadle | D78: +353 (569) 458-9673 | E78: 4418 Quincy Terrace | F78: Moycullen | G78: Ireland | H78: A41 | I78: Yes
A79: 86437-17399-FK | B79: Colene Elgey | C79: celgey25@webs.com | D79: +1 (432) 261-0702 | E79: 45 Marcy Crossing | F79: Midland | G79: United States | H79: 79705 | I79: No
A80: 62979-53167-ML | B80: Lothaire Mizzi | C80: lmizzi26@rakuten.co.jp | D80: +1 (214) 719-8530 | E80: 74 Atwood Lane | F80: Dallas | G80: United States | H80: 75323 | I80: Yes
A81: 54810-81899-HL | B81: Cletis Giacomazzo | C81: cgiacomazzo27@jigsy.com | D81: +1 (571) 703-2064 | E81: 817 Ridgeway Hill | F81: Dulles | G81: United States | H81: 20189 | I81: No
A82: 26103-41504-IB | B82: Ami Arnow | C82: aarnow28@arizona.edu | D82: +1 (650) 238-1964 | E82: 12 Oakridge Court | F82: Oakland | G82: United States | H82: 94627 | I82: Yes
A83: 76534-45229-SG | B83: Sheppard Yann | C83: syann29@senate.gov | D83: +1 (719) 803-5276 | E83: 4 Farmco Place | F83: Colorado Springs | G83: United States | H83: 80930 | I83: Yes
A84: 81744-27332-RR | B84: Bunny Naulls | C84: bnaulls2a@tiny.cc | D84: +353 (809) 128-0755 | E84: 595 Melby Avenue | F84: Adare | G84: Ireland | H84: H54 | I84: Yes
A85: 91513-75657-PH | B85: Hally Lorait | D85: +1 (716) 869-3749 | E85: 80 Jana Avenue | F85: Buffalo | G85: United States | H85: 14205 | I85: Yes
A86: 30373-66619-CB | B86: Zaccaria Sherewood | C86: zsherewood2c@apache.org | D86: +1 (209) 433-7924 | E86: 1325 Jay Terrace | F86: Fresno | G86: United States | H86: 93715 | I86: No
A87: 31582-23562-FM | B87: Jeffrey Dufaire | C87: jdufaire2d@fc2.com | E87: 8 Buell Junction | F87: Fort Worth | G87: United States | H87: 76121 | I87: No
A88: 58638-01029-CB | B88: Blancha McAmish | C88: bmcamish2e@tripadvisor.com | E88: 5484 Stephen Court | F88: Oklahoma City | G88: United States | H88: 73179 | I88: Yes
A89: 81431-12577-VD | B89: Beitris Keaveney | C89: bkeaveney2f@netlog.com | E89: 67319 Redwing Parkway | F89: Beaumont | G89: United States | H89: 77705 | I89: No
A90: 68894-91205-MP | B90: Elna Grise | C90: egrise2g@cargocollective.com | E90: 92 Becker Circle | F90: Reno | G90: United States | H90: 89519 | I90: No
A91: 87602-55754-VN | B91: Torie Gottelier | C91: tgottelier2h@vistaprint.com | D91: +1 (816) 743-8492 | E91: 426 Division Avenue | F91: Kansas City | G91: United States | H91: 64136 | I91: No
A92: 39181-35745-WH | B92: Loydie Langlais | D92: +353 (576) 222-5069 | E92: 290 Ilene Street | F92: Crumlin | G92: Ireland | H92: D6W | I92: Yes
A93: 30381-64762-NG | B93: Adham Greenhead | C93: agreenhead2j@dailymail.co.uk | D93: +1 (951) 797-0738 | E93: 0062 Spenser Place | F93: Corona | G93: United States | H93: 92878 | I93: No
A94: 17503-27693-ZH | B94: Hamish MacSherry | D94: +1 (512) 430-4374 | E94: 7 Brentwood Plaza | F94: Austin | G94: United States | H94: 78759 | I94: Yes
A95: 89442-35633-HJ | B95: Else Langcaster | C95: elangcaster2l@spotify.com | D95: +44 (547) 590-3103 | E95: 3658 Jenna Street | F95: Normanton | G95: United Kingdom | H95: LE15 | I95: Yes
A96: 13654-85265-IL | B96: Rudy Farquharson | E96: 30178 Claremont Road | F96: Charlesland | G96: Ireland | H96: A63 | I96: Yes
A97: 40946-22090-FP | B97: Norene Magauran | C97: nmagauran2n@51.la | E97: 567 Artisan Place | F97: Fresno | G97: United States | H97: 93762 | I97: No
A98: 29050-93691-TS | B98: Vicki Kirdsch | C98: vkirdsch2o@google.fr | E98: 0263 Golf Street | F98: Saint Louis | G98: United States | H98: 63150 | I98: No
A99: 64395-74865-WF | B99: Ilysa Whapple | C99: iwhapple2p@com.com | D99: +1 (559) 522-1152 | E99: 41598 Everett Drive | F99: Fresno | G99: United States | H99: 93726 | I99: No
A100: 81861-66046-SU | B100: Ruy Cancellieri | D100: +353 (338) 743-8327 | E100: 251 Welch Parkway | F100: Confey | G100: Ireland | H100: A86 | I100: No
...

Sheet Products
A1: Product ID | B1: Coffee Type | C1: Roast Type | D1: Size | E1: Unit Price | F1: Price per 100g | G1: Profit
A2: A-L-0.2 | B2: Ara | C2: L | D2: 0.2 | E2: 3.885 | F2: 1.9425 | G2: 0.34965
A3: A-L-0.5 | B3: Ara | C3: L | D3: 0.5 | E3: 7.77 | F3: 1.554 | G3: 0.6993
A4: A-L-1 | B4: Ara | C4: L | D4: 1 | E4: 12.95 | F4: 1.295 | G4: 1.1655
A5: A-L-2.5 | B5: Ara | C5: L | D5: 2.5 | E5: 29.785 | F5: 1.1914 | G5: 2.68065
A6: A-M-0.2 | B6: Ara | C6: M | D6: 0.2 | E6: 3.375 | F6: 1.6875 | G6: 0.30375
A7: A-M-0.5 | B7: Ara | C7: M | D7: 0.5 | E7: 6.75 | F7: 1.35 | G7: 0.6075
A8: A-M-1 | B8: Ara | C8: M | D8: 1 | E8: 11.25 | F8: 1.125 | G8: 1.0125
A9: A-M-2.5 | B9: Ara | C9: M | D9: 2.5 | E9: 25.875 | F9: 1.035 | G9: 2.32875
A10: A-D-0.2 | B10: Ara | C10: D | D10: 0.2 | E10: 2.985 | F10: 1.4925 | G10: 0.26865
A11: A-D-0.5 | B11: Ara | C11: D | D11: 0.5 | E11: 5.97 | F11: 1.194 | G11: 0.5373
A12: A-D-1 | B12: Ara | C12: D | D12: 1 | E12: 9.95 | F12: 0.995 | G12: 0.8955
A13: A-D-2.5 | B13: Ara | C13: D | D13: 2.5 | E13: 22.885 | F13: 0.9154 | G13: 2.05965
... A49: E-D-2.5 | B49: Exc | C49: D | D49: 2.5 | E49: 27.945 | F49: 1.1178 | G49: 3.07395

Sheet Orders (2)
A1: Order ID | B1: Order Date | C1: Customer ID | D1: =INDEX('Customers (2)'!B:B,MATCH('Customers (2)'!A1,'Customers (2)'!A:A,0)) -> Customer Name | E1: Product ID | F1: Quantity | G1: Size | H1: Unit Price | I1: Sales
A2: QEV-37451-860 | B2: 43713 | C2: 17670-51384-MA | D2: =INDEX('Customers (2)'!B:B,MATCH('Customers (2)'!A2,'Customers (2)'!A:A,0)) -> Aloisia Allner | E2: R-M-1 | F2: 2 | G2: =INDEX([1]products!$A$1:$G$49,MATCH([1]orders!$D2,[1]products!$A$1:$A$49,0),MATCH([1]orders!K$1,[1]products!$A$1:$G$1,0)) -> 1 | H2: =INDEX([1]products!$A$1:$G$49,MATCH([1]orders!$D2,[1]products!$A$1:$A$49,0),MATCH([1]orders!L$1,[1]products!$A$1:$G$1,0)) -> 9.95 | I2: =F2*H2 -> 19.9
A3: QEV-37451-860 | B3: 43713 | C3: 17670-51384-MA | D3: =INDEX('Customers (2)'!B:B,MATCH('Customers (2)'!A3,'Customers (2)'!A:A,0)) -> Piotr Bote | E3: E-M-0.5 | F3: 5 | G3: =INDEX([1]products!$A$1:$G$49,MATCH([1]orders!$D3,[1]products!$A$1:$A$49,0),MATCH([1]orders!K$1,[1]products!$A$1:$G$1,0)) -> 0.5 | H3: =INDEX([1]products!$A$1:$G$49,MATCH([1]orders!$D3,[1]products!$A$1:$A$49,0),MATCH([1]orders!L$1,[1]products!$A$1:$G$1,0)) -> 8.25 | I3: =F3*H3 -> 41.25
A4: FAA-43335-268 | B4: 44364 | C4: 21125-22134-PX | D4: =INDEX('Customers (2)'!B:B,MATCH('Customers (2)'!A4,'Customers (2)'!A:A,0)) -> Jami Redholes | E4: A-L-1 | F4: 1 | G4: =INDEX([1]products!$A$1:$G$49,MATCH([1]orders!$D4,[1]products!$A$1:$A$49,0),MATCH([1]orders!K$1,[1]products!$A$1:$G$1,0)) -> 1 | H4: =INDEX([1]products!$A$1:$G$49,MATCH([1]orders!$D4,[1]products!$A$1:$A$49,0),MATCH([1]orders!L$1,[1]products!$A$1:$G$1,0)) -> 12.95 | I4: =F4*H4 -> 12.95
A5: KAC-83089-793 | B5: 44392 | C5: 23806-46781-OU | D5: =INDEX('Customers (2)'!B:B,MATCH('Customers (2)'!A5,'Customers (2)'!A:A,0)) -> Dene Azema | E5: E-M-1 | F5: 2 | G5: =INDEX([1]products!$A$1:$G$49,MATCH([1]orders!$D5,[1]products!$A$1:$A$49,0),MATCH([1]orders!K$1,[1]products!$A$1:$G$1,0)) -> 1 | H5: =INDEX([1]products!$A$1:$G$49,MATCH([1]orders!$D5,[1]products!$A$1:$A$49,0),MATCH([1]orders!L$1,[1]products!$A$1:$G$1,0)) -> 13.75 | I5: =F5*H5 -> 27.5
A6: KAC-83089-793 | B6: 44392 | C6: 23806-46781-OU | D6: =INDEX('Customers (2)'!B:B,MATCH('Customers (2)'!A6,'Customers (2)'!A:A,0)) -> Christoffer O' Shea | E6: R-L-2.5 | F6: 2 | G6: =INDEX([1]products!$A$1:$G$49,MATCH([1]orders!$D6,[1]products!$A$1:$A$49,0),MATCH([1]orders!K$1,[1]products!$A$1:$G$1,0)) -> 2.5 | H6: =INDEX([1]products!$A$1:$G$49,MATCH([1]orders!$D6,[1]products!$A$1:$A$49,0),MATCH([1]orders!L$1,[1]products!$A$1:$G$1,0)) -> 27.485 | I6: =F6*H6 -> 54.97
A7: CVP-18956-553 | B7: 44412 | C7: 86561-91660-RB | D7: =INDEX('Customers (2)'!B:B,MATCH('Customers (2)'!A7,'Customers (2)'!A:A,0)) -> Beryle Cottier | E7: L-D-1 | F7: 3 | G7: =INDEX([1]products!$A$1:$G$49,MATCH([1]orders!$D7,[1]products!$A$1:$A$49,0),MATCH([1]orders!K$1,[1]products!$A$1:$G$1,0)) -> 1 | H7: =INDEX([1]products!$A$1:$G$49,MATCH([1]orders!$D7,[1]products!$A$1:$A$49,0),MATCH([1]orders!L$1,[1]products!$A$1:$G$1,0)) -> 12.95 | I7: =F7*H7 -> 38.85
A8: IPP-31994-879 | B8: 44582 | C8: 65223-29612-CB | D8: =INDEX('Customers (2)'!B:B,MATCH('Customers (2)'!A8,'Customers (2)'!A:A,0)) -> Shaylynn Lobe | E8: E-D-0.5 | F8: 3 | G8: =INDEX([1]products!$A$1:$G$49,MATCH([1]orders!$D8,[1]products!$A$1:$A$49,0),MATCH([1]orders!K$1,[1]products!$A$1:$G$1,0)) -> 0.5 | H8: =INDEX([1]products!$A$1:$G$49,MATCH([1]orders!$D8,[1]products!$A$1:$A$49,0),MATCH([1]orders!L$1,[1]products!$A$1:$G$1,0)) -> 7.29 | I8: =F8*H8 -> 21.87
A9: SNZ-65340-705 | B9: 44701 | C9: 21134-81676-FR | D9: =INDEX('Customers (2)'!B:B,MATCH('Customers (2)'!A9,'Customers (2)'!A:A,0)) -> Melvin Wharfe | E9: L-L-0.2 | F9: 1 | G9: =INDEX([1]products!$A$1:$G$49,MATCH([1]orders!$D9,[1]products!$A$1:$A$49,0),MATCH([1]orders!K$1,[1]products!$A$1:$G$1,0)) -> 0.2 | H9: =INDEX([1]products!$A$1:$G$49,MATCH([1]orders!$D9,[1]products!$A$1:$A$49,0),MATCH([1]orders!L$1,[1]products!$A$1:$G$1,0)) -> 4.755 | I9: =F9*H9 -> 4.755
A10: EZT-46571-659 | B10: 43467 | C10: 03396-68805-ZC | D10: =INDEX('Customers (2)'!B:B,MATCH('Customers (2)'!A10,'Customers (2)'!A:A,0)) -> Guthrey Petracci | E10: R-M-0.5 | F10: 3 | G10: =INDEX([1]products!$A$1:$G$49,MATCH([1]orders!$D10,[1]products!$A$1:$A$49,0),MATCH([1]orders!K$1,[1]products!$A$1:$G$1,0)) -> 0.5 | H10: =INDEX([1]products!$A$1:$G$49,MATCH([1]orders!$D10,[1]products!$A$1:$A$49,0),MATCH([1]orders!L$1,[1]products!$A$1:$G$1,0)) -> 5.97 | I10: =F10*H10 -> 17.91
A11: NWQ-70061-912 | B11: 43713 | C11: 61021-27840-ZN | D11: =INDEX('Customers (2)'!B:B,MATCH('Customers (2)'!A11,'Customers (2)'!A:A,0)) -> Rodger Raven | E11: R-M-0.5 | F11: 1 | G11: =INDEX([1]products!$A$1:$G$49,MATCH([1]orders!$D11,[1]products!$A$1:$A$49,0),MATCH([1]orders!K$1,[1]products!$A$1:$G$1,0)) -> 0.5 | H11: =INDEX([1]products!$A$1:$G$49,MATCH([1]orders!$D11,[1]products!$A$1:$A$49,0),MATCH([1]orders!L$1,[1]products!$A$1:$G$1,0)) -> 5.97 | I11: =F11*H11 -> 5.97
A12: BKK-47233-845 | B12: 44263 | C12: 76239-90137-UQ | D12: =INDEX('Customers (2)'!B:B,MATCH('Customers (2)'!A12,'Customers (2)'!A:A,0)) -> Ferrell Ferber | E12: A-D-1 | F12: 4 | G12: =INDEX([1]products!$A$1:$G$49,MATCH([1]orders!$D12,[1]products!$A$1:$A$49,0),MATCH([1]orders!K$1,[1]products!$A$1:$G$1,0)) -> 1 | H12: =INDEX([1]products!$A$1:$G$49,MATCH([1]orders!$D12,[1]products!$A$1:$A$49,0),MATCH([1]orders!L$1,[1]products!$A$1:$G$1,0)) -> 9.95 | I12: =F12*H12 -> 39.8
A13: VQR-01002-970 | B13: 44132 | C13: 49315-21985-BB | D13: =INDEX('Customers (2)'!B:B,MATCH('Customers (2)'!A13,'Customers (2)'!A:A,0)) -> Duky Phizackerly | E13: E-L-2.5 | F13: 5 | G13: =INDEX([1]products!$A$1:$G$49,MATCH([1]orders!$D13,[1]products!$A$1:$A$49,0),MATCH([1]orders!K$1,[1]products!$A$1:$G$1,0)) -> 2.5 | H13: =INDEX([1]products!$A$1:$G$49,MATCH([1]orders!$D13,[1]products!$A$1:$A$49,0),MATCH([1]orders!L$1,[1]products!$A$1:$G$1,0)) -> 34.155 | I13: =F13*H13 -> 170.775
... A1001: IRV-20769-219 | B1001: 44119 | C1001: 77131-58092-GE | D1001: =INDEX('Customers (2)'!B:B,MATCH('Customers (2)'!A1001,'Customers (2)'!A:A,0)) -> Vidovic Antonelli | E1001: E-M-0.2 | F1001: 3 | G1001: =INDEX([1]products!$A$1:$G$49,MATCH([1]orders!$D1001,[1]products!$A$1:$A$49,0),MATCH([1]orders!K$1,[1]products!$A$1:$G$1,0)) -> 0.2 | H1001: =INDEX([1]products!$A$1:$G$49,MATCH([1]orders!$D1001,[1]products!$A$1:$A$49,0),MATCH([1]orders!L$1,[1]products!$A$1:$G$1,0)) -> 4.125 | I1001: =F1001*H1001 -> 12.375

Sheet Customers (2)
A1: Customer ID | B1: Customer Name | C1: Email | D1: Phone Number | E1: Address Line 1 | F1: City | G1: Country | H1: Postcode | I1: Loyalty Card
A2: 17670-51384-MA | B2: Aloisia Allner | C2: aallner0@lulu.com | D2: +1 (862) 817-0124 | E2: 57999 Pepper Wood Alley | F2: Paterson | G2: United States | H2: 7505 | I2: Yes
A3: 73342-18763-UW | B3: Piotr Bote | C3: pbote1@yelp.com | D3: +353 (913) 396-4653 | E3: 2112 Ridgeway Hill | F3: Crumlin | G3: Ireland | H3: D6W | I3: No
A4: 21125-22134-PX | B4: Jami Redholes | C4: jredholes2@tmall.com | D4: +1 (210) 986-6806 | E4: 5214 Bartillon Park | F4: San Antonio | G4: United States | H4: 78205 | I4: Yes
A5: 71253-00052-RN | B5: Dene Azema | C5: dazema3@facebook.com | D5: +1 (217) 418-0714 | E5: 27 Maywood Place | F5: Springfield | G5: United States | H5: 62711 | I5: Yes
A6: 23806-46781-OU | B6: Christoffer O' Shea | D6: +353 (698) 362-9201 | E6: 38980 Manitowish Junction | F6: Cill Airne | G6: Ireland | H6: N41 | I6: No
A7: 86561-91660-RB | B7: Beryle Cottier | D7: +1 (570) 289-7473 | E7: 2651 Stoughton Place | F7: Scranton | G7: United States | H7: 18505 | I7: No
A8: 65223-29612-CB | B8: Shaylynn Lobe | C8: slobe6@nifty.com | D8: +1 (937) 954-4541 | E8: 7005 Mariners Cove Place | F8: Dayton | G8: United States | H8: 45440 | I8: Yes
A9: 21134-81676-FR | B9: Melvin Wharfe | D9: +353 (507) 574-3034 | E9: 7 Straubel Road | F9: Kill | G9: Ireland | H9: P24 | I9: Yes
A10: 03396-68805-ZC | B10: Guthrey Petracci | C10: gpetracci8@livejournal.com | D10: +1 (310) 868-1842 | E10: 949 Paget Parkway | F10: Los Angeles | G10: United States | H10: 90045 | I10: No
A11: 61021-27840-ZN | B11: Rodger Raven | C11: rraven9@ed.gov | D11: +1 (213) 263-0288 | E11: 1 Reinke Avenue | F11: Los Angeles | G11: United States | H11: 90065 | I11: No
A12: 76239-90137-UQ | B12: Ferrell Ferber | C12: fferbera@businesswire.com | D12: +1 (408) 383-5302 | E12: 68 High Crossing Court | F12: San Jose | G12: United States | H12: 95160 | I12: No
A13: 49315-21985-BB | B13: Duky Phizackerly | C13: dphizackerlyb@utexas.edu | D13: +1 (408) 533-6012 | E13: 28643 Bluejay Crossing | F13: San Jose | G13: United States | H13: 95194 | I13: Yes
A14: 34136-36674-OM | B14: Rosaleen Scholar | C14: rscholarc@nyu.edu | D14: +1 (804) 420-0420 | E14: 80915 Montana Park | F14: Richmond | G14: United States | H14: 23285 | I14: No
A15: 39396-12890-PE | B15: Terence Vanyutin | C15: tvanyutind@wix.com | E15: 331 Bunting Hill | F15: Migrate | G15: United States | H15: 41905 | I15: No
A16: 95875-73336-RG | B16: Patrice Trobe | C16: ptrobee@wunderground.com | D16: +1 (314) 240-7896 | E16: 827 Declaration Plaza | F16: Saint Louis | G16: United States | H16: 63131 | I16: Yes
A17: 25473-43727-BY | B17: Llywellyn Oscroft | C17: loscroftf@ebay.co.uk | E17: 022 Roth Place | F17: Philadelphia | G17: United States | H17: 19172 | I17: No
A18: 99643-51048-IQ | B18: Minni Alabaster | C18: malabasterg@hexun.com | D18: +1 (971) 483-6255 | E18: 3 Charing Cross Trail | F18: Portland | G18: United States | H18: 97271 | I18: No
A19: 62173-15287-CU | B19: Rhianon Broxup | C19: rbroxuph@jimdo.com | D19: +1 (713) 663-1338 | E19: 83517 Thierer Court | F19: Houston | G19: United States | H19: 77240 | I19: No
A20: 57611-05522-ST | B20: Pall Redford | C20: predfordi@ow.ly | E20: 7337 Hayes Junction | F20: Caherconlish | G20: Ireland | H20: F45 | I20: Yes
A21: 76664-37050-DT | B21: Aurea Corradino | C21: acorradinoj@harvard.edu | D21: +1 (646) 202-5965 | E21: 698 Canary Terrace | F21: New York City | G21: United States | H21: 10060 | I21: Yes
A22: 84565-53984-SX | B22: Kendal Scardefield | D22: +353 (733) 405-3302 | E22: 3 Northridge Crossing | F22: Clondalkin | G22: Ireland | H22: D24 | I22: Yes
A23: 03090-88267-BQ | B23: Avrit Davidowsky | C23: adavidowskyl@netvibes.com | D23: +1 (616) 481-9962 | E23: 9 Warrior Junction | F23: Grand Rapids | G23: United States | H23: 49560 | I23: No
A24: 37651-47492-NC | B24: Annabel Antuk | C24: aantukm@kickstarter.com | D24: +1 (941) 740-6268 | E24: 77965 Lawn Park | F24: Punta Gorda | G24: United States | H24: 33982 | I24: Yes
A25: 95399-57205-HI | B25: Iorgo Kleinert | C25: ikleinertn@timesonline.co.uk | D25: +1 (360) 352-6598 | E25: 1 Morningstar Lane | F25: Vancouver | G25: United States | H25: 98682 | I25: Yes
A26: 24010-66714-HW | B26: Chrisy Blofeld | C26: cblofeldo@amazon.co.uk | D26: +1 (303) 936-3357 | E26: 013 Talisman Terrace | F26: Englewood | G26: United States | H26: 80150 | I26: No
A27: 07591-92789-UA | B27: Culley Farris | D27: +1 (941) 267-4822 | E27: 4 Mitchell Drive | F27: Punta Gorda | G27: United States | H27: 33982 | I27: Yes
A28: 49231-44455-IC | B28: Selene Shales | C28: sshalesq@umich.edu | D28: +1 (707) 881-5004 | E28: 74 Bultman Plaza | F28: Petaluma | G28: United States | H28: 94975 | I28: Yes
A29: 50124-88608-EO | B29: Vivie Danneil | C29: vdanneilr@mtv.com | D29: +353 (751) 346-0399 | E29: 5626 Darwin Avenue | F29: Tralee | G29: Ireland | H29: V92 | I29: No
A30: 00888-74814-UZ | B30: Theresita Newbury | C30: tnewburys@usda.gov | D30: +353 (803) 587-0026 | E30: 79526 Bultman Lane | F30: Clonskeagh | G30: Ireland | H30: D04 | I30: No
A31: 14158-30713-OB | B31: Mozelle Calcutt | C31: mcalcuttt@baidu.com | D31: +353 (928) 869-1762 | E31: 4389 Russell Way | F31: Rathwire | G31: Ireland | H31: Y25 | I31: Yes
A32: 51427-89175-QJ | B32: Adrian Swaine | D32: +1 (303) 486-9517 | E32: 95 Straubel Hill | F32: Aurora | G32: United States | H32: 80044 | I32: No
A33: 52082-49024-ON | B33: Ray Leivesley | C33: rleivesleyv@canalblog.com | D33: +1 (212) 535-7791 | E33: 91 Stephen Drive | F33: Jamaica | G33: United States | H33: 11407 | I33: No
A34: 04540-43685-DV | B34: Nelly Basezzi | C34: nbasezziw@webeden.co.uk | D34: +353 (125) 815-7345 | E34: 923 Mallard Junction | F34: Bailieborough | G34: Ireland | H34: C15 | I34: Yes
A35: 39123-12846-YJ | B35: Gallard Gatheral | C35: ggatheralx@123-reg.co.uk | E35: 40 Clemons Place | F35: Grand Forks | G35: United States | H35: 58207 | I35: No
A36: 44981-99666-XB | B36: Una Welberry | C36: uwelberryy@ebay.co.uk | D36: +44 (392) 503-8132 | E36: 40915 Schlimgen Park | F36: Upton | G36: United Kingdom | H36: DN21 | I36: Yes
A37: 24825-51803-CQ | B37: Faber Eilhart | C37: feilhartz@who.int | D37: +1 (304) 510-6095 | E37: 6966 Victoria Street | F37: Charleston | G37: United States | H37: 25362 | I37: No
A38: 77634-13918-GJ | B38: Zorina Ponting | C38: zponting10@altervista.org | D38: +1 (501) 172-1476 | E38: 7118 Holmberg Court | F38: Little Rock | G38: United States | H38: 72204 | I38: No
A39: 13694-25001-LX | B39: Silvio Strase | C39: sstrase11@booking.com | D39: +1 (303) 579-8015 | E39: 5 Forest Lane | F39: Denver | G39: United States | H39: 80291 | I39: No
A40: 08523-01791-TI | B40: Dorie de la Tremoille | C40: dde12@unesco.org | D40: +1 (612) 492-5160 | E40: 0817 Dennis Street | F40: Minneapolis | G40: United States | H40: 55458 | I40: No
A41: 49860-68865-AB | B41: Hy Zanetto | E41: 469 Paget Place | F41: Tucson | G41: United States | H41: 85715 | I41: Yes
A42: 21240-83132-SP | B42: Jessica McNess | D42: +1 (504) 545-1478 | E42: 664 Erie Place | F42: New Orleans | G42: United States | H42: 70116 | I42: No
A43: 08350-81623-TF | B43: Lorenzo Yeoland | C43: lyeoland15@pbs.org | D43: +1 (860) 576-2887 | E43: 8510 Merrick Road | F43: Hartford | G43: United States | H43: 6183 | I43: Yes
A44: 73284-01385-SJ | B44: Abigail Tolworthy | C44: atolworthy16@toplist.cz | D44: +1 (801) 722-4425 | E44: 74 Shopko Way | F44: Ogden | G44: United States | H44: 84409 | I44: Yes
A45: 04152-34436-IE | B45: Maurie Bartol | D45: +1 (617) 493-7594 | E45: 7625 Starling Court | F45: Boston | G45: United States | H45: 2216 | I45: No
A46: 06631-86965-XP | B46: Olag Baudassi | C46: obaudassi18@seesaa.net | D46: +1 (585) 356-6251 | E46: 55 Dottie Court | F46: Rochester | G46: United States | H46: 14604 | I46: Yes
A47: 54619-08558-ZU | B47: Petey Kingsbury | C47: pkingsbury19@comcast.net | D47: +1 (917) 705-8224 | E47: 28 Loftsgordon Place | F47: Bronx | G47: United States | H47: 10469 | I47: No
A48: 85589-17020-CX | B48: Donna Baskeyfied | D48: +1 (205) 923-1460 | E48: 7586 Logan Avenue | F48: Birmingham | G48: United States | H48: 35205 | I48: Yes
A49: 36078-91009-WU | B49: Arda Curley | C49: acurley1b@hao123.com | D49: +1 (760) 840-3808 | E49: 45098 Scott Drive | F49: San Bernardino | G49: United States | H49: 92415 | I49: Yes
A50: 15770-27099-GX | B50: Raynor McGilvary | C50: rmcgilvary1c@tamu.edu | E50: 496 Rockefeller Court | F50: Norfolk | G50: United States | H50: 23514 | I50: No
A51: 91460-04823-BX | B51: Isis Pikett | C51: ipikett1d@xinhuanet.com | D51: +1 (202) 871-9039 | E51: 5892 Hauk Drive | F51: Washington | G51: United States | H51: 20409 | I51: No
A52: 45089-52817-WN | B52: Inger Bouldon | C52: ibouldon1e@gizmodo.com | D52: +1 (754) 391-4736 | E52: 925 Barby Circle | F52: Fort Lauderdale | G52: United States | H52: 33355 | I52: No
A53: 76447-50326-IC | B53: Karry Flanders | C53: kflanders1f@over-blog.com | D53: +353 (467) 720-7274 | E53: 88 Blue Bill Park Avenue | F53: Crumlin | G53: Ireland | H53: D6W | I53: Yes
A54: 26333-67911-OL | B54: Hartley Mattioli | C54: hmattioli1g@webmd.com | E54: 126 Valley Edge Street | F54: Kinloch | G54: United Kingdom | H54: PH43 | I54: No
A55: 40768-49176-BL | B55: Horatio Rubberts | C55: hrubberts1h@google.com.hk | D55: +1 (801) 635-8791 | E55: 459 Russell Center | F55: Provo | G55: United States | H55: 84605 | I55: No
A56: 22107-86640-SB | B56: Archambault Gillard | C56: agillard1i@issuu.com | D56: +1 (419) 663-2236 | E56: 97490 Susan Avenue | F56: Toledo | G56: United States | H56: 43666 | I56: No
A57: 09960-34242-LZ | B57: Salomo Cushworth | D57: +1 (609) 409-7044 | E57: 44 Oneill Parkway | F57: Trenton | G57: United States | H57: 8650 | I57: No
A58: 04671-85591-RT | B58: Theda Grizard | C58: tgrizard1k@odnoklassniki.ru | D58: +1 (813) 243-2150 | E58: 6 Knutson Pass | F58: Tampa | G58: United States | H58: 33686 | I58: Yes
A59: 25729-68859-UA | B59: Rozele Relton | C59: rrelton1l@stanford.edu | D59: +1 (850) 626-1181 | E59: 2484 Reindahl Court | F59: Pensacola | G59: United States | H59: 32590 | I59: No
A60: 05501-86351-NX | B60: Willa Rolling | D60: +1 (813) 759-3534 | E60: 3 Mockingbird Plaza | F60: Zephyrhills | G60: United States | H60: 33543 | I60: Yes
A61: 04521-04300-OK | B61: Stanislaus Gilroy | C61: sgilroy1n@eepurl.com | E61: 9120 Harbort Terrace | F61: Saint Paul | G61: United States | H61: 55123 | I61: Yes
A62: 58689-55264-VK | B62: Correy Cottingham | C62: ccottingham1o@wikipedia.org | D62: +1 (260) 764-1820 | E62: 394 Logan Road | F62: Fort Wayne | G62: United States | H62: 46862 | I62: No
A63: 79436-73011-MM | B63: Pammi Endacott | D63: +44 (177) 260-5076 | E63: 5841 Atwood Lane | F63: Wootton | G63: United Kingdom | H63: NN4 | I63: Yes
A64: 65552-60476-KY | B64: Nona Linklater | D64: +1 (239) 347-9766 | E64: 856 Bonner Parkway | F64: Naples | G64: United States | H64: 34114 | I64: Yes
A65: 69904-02729-YS | B65: Annadiane Dykes | C65: adykes1r@eventbrite.com | D65: +1 (312) 111-6203 | E65: 31 Northport Terrace | F65: Chicago | G65: United States | H65: 60681 | I65: No
A66: 01433-04270-AX | B66: Felecia Dodgson | D66: +1 (973) 434-8662 | E66: 48053 8th Crossing | F66: Newark | G66: United States | H66: 7104 | I66: Yes
A67: 14204-14186-LA | B67: Angelia Cockrem | C67: acockrem1t@engadget.com | D67: +1 (571) 316-8217 | E67: 1 Sherman Alley | F67: Vienna | G67: United States | H67: 22184 | I67: Yes
A68: 32948-34398-HC | B68: Belvia Umpleby | C68: bumpleby1u@soundcloud.com | D68: +1 (682) 627-0888 | E68: 710 Prairie Rose Terrace | F68: Fort Worth | G68: United States | H68: 76178 | I68: Yes
A69: 77343-52608-FF | B69: Nat Saleway | C69: nsaleway1v@dedecms.com | D69: +1 (323) 473-0294 | E69: 0780 Anthes Plaza | F69: Burbank | G69: United States | H69: 91505 | I69: No
A70: 42770-36274-QA | B70: Hayward Goulter | C70: hgoulter1w@abc.net.au | D70: +1 (423) 764-7751 | E70: 2081 Mariners Cove Drive | F70: Kingsport | G70: United States | H70: 37665 | I70: No
A71: 14103-58987-ZU | B71: Gay Rizzello | C71: grizzello1x@symantec.com | D71: +44 (247) 225-8003 | E71: 21 Schmedeman Crossing | F71: Liverpool | G71: United Kingdom | H71: L33 | I71: Yes
A72: 69958-32065-SW | B72: Shannon List | C72: slist1y@mapquest.com | D72: +1 (614) 279-9816 | E72: 7123 Algoma Center | F72: Columbus | G72: United States | H72: 43231 | I72: No
A73: 69533-84907-FA | B73: Shirlene Edmondson | C73: sedmondson1z@theguardian.com | D73: +353 (248) 428-7978 | E73: 4752 International Point | F73: Newmarket on Fergus | G73: Ireland | H73: P17 | I73: No
A74: 76005-95461-CI | B74: Aurlie McCarl | D74: +1 (504) 209-2724 | E74: 731 David Park | F74: New Orleans | G74: United States | H74: 70183 | I74: No
A75: 15395-90855-VB | B75: Alikee Carryer | D75: +1 (704) 799-5219 | E75: 247 Helena Drive | F75: Charlotte | G75: United States | H75: 28230 | I75: Yes
A76: 80640-45811-LB | B76: Jennifer Rangall | C76: jrangall22@newsvine.com | D76: +1 (781) 512-6637 | E76: 0 Grasskamp Lane | F76: Springfield | G76: United States | H76: 1114 | I76: Yes
A77: 28476-04082-GR | B77: Kipper Boorn | C77: kboorn23@ezinearticles.com | D77: +353 (359) 134-1550 | E77: 9513 Meadow Ridge Parkway | F77: Listowel | G77: Ireland | H77: V31 | I77: Yes
A78: 12018-75670-EU | B78: Melania Beadle | D78: +353 (569) 458-9673 | E78: 4418 Quincy Terrace | F78: Moycullen | G78: Ireland | H78: A41 | I78: Yes
A79: 86437-17399-FK | B79: Colene Elgey | C79: celgey25@webs.com | D79: +1 (432) 261-0702 | E79: 45 Marcy Crossing | F79: Midland | G79: United States | H79: 79705 | I79: No
A80: 62979-53167-ML | B80: Lothaire Mizzi | C80: lmizzi26@rakuten.co.jp | D80: +1 (214) 719-8530 | E80: 74 Atwood Lane | F80: Dallas | G80: United States | H80: 75323 | I80: Yes
A81: 54810-81899-HL | B81: Cletis Giacomazzo | C81: cgiacomazzo27@jigsy.com | D81: +1 (571) 703-2064 | E81: 817 Ridgeway Hill | F81: Dulles | G81: United States | H81: 20189 | I81: No
A82: 26103-41504-IB | B82: Ami Arnow | C82: aarnow28@arizona.edu | D82: +1 (650) 238-1964 | E82: 12 Oakridge Court | F82: Oakland | G82: United States | H82: 94627 | I82: Yes
A83: 76534-45229-SG | B83: Sheppard Yann | C83: syann29@senate.gov | D83: +1 (719) 803-5276 | E83: 4 Farmco Place | F83: Colorado Springs | G83: United States | H83: 80930 | I83: Yes
A84: 81744-27332-RR | B84: Bunny Naulls | C84: bnaulls2a@tiny.cc | D84: +353 (809) 128-0755 | E84: 595 Melby Avenue | F84: Adare | G84: Ireland | H84: H54 | I84: Yes
A85: 91513-75657-PH | B85: Hally Lorait | D85: +1 (716) 869-3749 | E85: 80 Jana Avenue | F85: Buffalo | G85: United States | H85: 14205 | I85: Yes
A86: 30373-66619-CB | B86: Zaccaria Sherewood | C86: zsherewood2c@apache.org | D86: +1 (209) 433-7924 | E86: 1325 Jay Terrace | F86: Fresno | G86: United States | H86: 93715 | I86: No
A87: 31582-23562-FM | B87: Jeffrey Dufaire | C87: jdufaire2d@fc2.com | E87: 8 Buell Junction | F87: Fort Worth | G87: United States | H87: 76121 | I87: No
A88: 58638-01029-CB | B88: Blancha McAmish | C88: bmcamish2e@tripadvisor.com | E88: 5484 Stephen Court | F88: Oklahoma City | G88: United States | H88: 73179 | I88: Yes
A89: 81431-12577-VD | B89: Beitris Keaveney | C89: bkeaveney2f@netlog.com | E89: 67319 Redwing Parkway | F89: Beaumont | G89: United States | H89: 77705 | I89: No
A90: 68894-91205-MP | B90: Elna Grise | C90: egrise2g@cargocollective.com | E90: 92 Becker Circle | F90: Reno | G90: United States | H90: 89519 | I90: No
A91: 87602-55754-VN | B91: Torie Gottelier | C91: tgottelier2h@vistaprint.com | D91: +1 (816) 743-8492 | E91: 426 Division Avenue | F91: Kansas City | G91: United States | H91: 64136 | I91: No
A92: 39181-35745-WH | B92: Loydie Langlais | D92: +353 (576) 222-5069 | E92: 290 Ilene Street | F92: Crumlin | G92: Ireland | H92: D6W | I92: Yes
A93: 30381-64762-NG | B93: Adham Greenhead | C93: agreenhead2j@dailymail.co.uk | D93: +1 (951) 797-0738 | E93: 0062 Spenser Place | F93: Corona | G93: United States | H93: 92878 | I93: No
A94: 17503-27693-ZH | B94: Hamish MacSherry | D94: +1 (512) 430-4374 | E94: 7 Brentwood Plaza | F94: Austin | G94: United States | H94: 78759 | I94: Yes
A95: 89442-35633-HJ | B95: Else Langcaster | C95: elangcaster2l@spotify.com | D95: +44 (547) 590-3103 | E95: 3658 Jenna Street | F95: Normanton | G95: United Kingdom | H95: LE15 | I95: Yes
A96: 13654-85265-IL | B96: Rudy Farquharson | E96: 30178 Claremont Road | F96: Charlesland | G96: Ireland | H96: A63 | I96: Yes
A97: 40946-22090-FP | B97: Norene Magauran | C97: nmagauran2n@51.la | E97: 567 Artisan Place | F97: Fresno | G97: United States | H97: 93762 | I97: No
A98: 29050-93691-TS | B98: Vicki Kirdsch | C98: vkirdsch2o@google.fr | E98: 0263 Golf Street | F98: Saint Louis | G98: United States | H98: 63150 | I98: No
A99: 64395-74865-WF | B99: Ilysa Whapple | C99: iwhapple2p@com.com | D99: +1 (559) 522-1152 | E99: 41598 Everett Drive | F99: Fresno | G99: United States | H99: 93726 | I99: No
A100: 81861-66046-SU | B100: Ruy Cancellieri | D100: +353 (338) 743-8327 | E100: 251 Welch Parkway | F100: Confey | G100: Ireland | H100: A86 | I100: No
...

Sheet Products (2)
A1: Product ID | B1: Coffee Type | C1: Roast Type | D1: Size | E1: Unit Price | F1: Price per 100g | G1: Profit
A2: A-L-0.2 | B2: Arabica | C2: Light | D2: 0.2 | E2: 3.885 | F2: 1.9425 | G2: 0.34965
A3: A-L-0.5 | B3: Arabica | C3: Light | D3: 0.5 | E3: 7.77 | F3: 1.554 | G3: 0.6993
A4: A-L-1 | B4: Arabica | C4: Light | D4: 1 | E4: 12.95 | F4: 1.295 | G4: 1.1655
A5: A-L-2.5 | B5: Arabica | C5: Light | D5: 2.5 | E5: 29.785 | F5: 1.1914 | G5: 2.68065
A6: A-M-0.2 | B6: Arabica | C6: Medium | D6: 0.2 | E6: 3.375 | F6: 1.6875 | G6: 0.30375
A7: A-M-0.5 | B7: Arabica | C7: Medium | D7: 0.5 | E7: 6.75 | F7: 1.35 | G7: 0.6075
A8: A-M-1 | B8: Arabica | C8: Medium | D8: 1 | E8: 11.25 | F8: 1.125 | G8: 1.0125
A9: A-M-2.5 | B9: Arabica | C9: Medium | D9: 2.5 | E9: 25.875 | F9: 1.035 | G9: 2.32875
A10: A-D-0.2 | B10: Arabica | C10: Dark | D10: 0.2 | E10: 2.985 | F10: 1.4925 | G10: 0.26865
A11: A-D-0.5 | B11: Arabica | C11: Dark | D11: 0.5 | E11: 5.97 | F11: 1.194 | G11: 0.5373
A12: A-D-1 | B12: Arabica | C12: Dark | D12: 1 | E12: 9.95 | F12: 0.995 | G12: 0.8955
A13: A-D-2.5 | B13: Arabica | C13: Dark | D13: 2.5 | E13: 22.885 | F13: 0.9154 | G13: 2.05965
... A49: E-D-2.5 | B49: Excelsa | C49: Dark | D49: 2.5 | E49: 27.945 | F49: 1.1178 | G49: 3.07395

Sheet Sheet2
A3: Sum of Sales | B3: Column Labels
A4: Row Labels | B4: 2019 | C4: 2020 | D4: 2021 | E4: 2022 | F4: (blank) | G4: Grand Total
A5: Arabica | B5: 2926.63 | C5: 3356.415 | D5: 4045.63 | E5: 1439.82 | G5: 11768.495
A6: Excelsa | B6: 3481.46 | C6: 3663.41 | D6: 3469.64 | E6: 1691.93 | G6: 12306.44
A7: Liberica | B7: 3378.005 | C7: 2604.455 | D7: 3836.695 | E7: 2234.92 | G7: 12054.075
A8: Robusta | B8: 2401.07 | C8: 2493.265 | D8: 2414.145 | E8: 1696.765 | G8: 9005.245
A9: (blank)
A10: Grand Total | B10: 12187.165 | C10: 12117.545 | D10: 13766.11 | E10: 7063.435 | G10: 45134.255
A13: Sum of Sales | B13: Column Labels
A14: Row Labels | B14: 2019 | C14: 2020 | D14: 2021 | E14: 2022 | F14: Grand Total
A15: Ireland | B15: 1781.075 | C15: 1674.865 | D15: 2032.455 | E15: 1208.47 | F15: 6696.865
A16: United Kingdom | B16: 951.28 | C16: 1074.32 | D16: 643.045 | E16: 129.86 | F16: 2798.505
A17: United States | B17: 9454.81 | C17: 9368.36 | D17: 11090.61 | E17: 5725.105 | F17: 35638.885
A18: Grand Total | B18: 12187.165 | C18: 12117.545 | D18: 13766.11 | E18: 7063.435 | F18: 45134.255
A24: Row Labels | B24: Sum of Sales
A25: Albany | B25: 399.24
A26: Ballivor | B26: 389.265
A27: Birmingham | B27: 509.11
A28: Dallas | B28: 505.925
A29: El Paso | B29: 404.7
A30: Fort Worth | B30: 396.51 | M30: Row Labels | N30: Sum of Sales
A31: Houston | B31: 819.77 | M31: Dark | N31: 13179.315
A32: New York City | B32: 772.735 | M32: Light | N32: 17354.465
A33: Oklahoma City | B33: 475.17 | M33: Medium | N33: 14600.475
A34: Philadelphia | B34: 511.235 | M34: Grand Total | N34: 45134.255
A35: Portland | B35: 580.26
A36: Richmond | B36: 407.59
A37: Sacramento | B37: 627.75
A38: Toledo | B38: 774.185
A39: Washington | B39: 1066.92 | D39: Row Labels | E39: Count of Customer ID
A40: Grand Total | B40: 8640.365 | D40: 2019 | E40: 259
D41: 2020 | E41: 263
D42: 2021 | E42: 312
A43: Row Labels | B43: Count of Customer ID | D43: 2022 | E43: 166
A44: Ireland | B44: 153 | D44: Grand Total | E44: 1000
A45: United Kingdom | B45: 73
A46: United States | B46: 774
A47: (blank)
A48: Grand Total | B48: 1000
A49: Row Labels | B49: Count of Customer ID | D49: Row Labels | E49: Sum of Quantity
A50: Birmingham | B50: 13 | D50: Ailey Brash | E50: 19
A51: Dallas | B51: 11 | D51: Jimmy Dymoke | E51: 23
A52: El Paso | B52: 11 | D52: Marguerite Graves | E52: 17
A53: Fresno | B53: 9 | D53: Marja Urion | E53: 19
A54: Houston | B54: 15 | D54: Nealson Cuttler | E54: 18
A55: Los Angeles | B55: 11 | D55: Grand Total | E55: 96
A56: New York City | B56: 17
A57: Oklahoma City | B57: 15
A58: Philadelphia | B58: 9
A59: Sacramento | B59: 9 | D59: Row Labels | E59: Sum of Sales
A60: Saint Louis | B60: 10 | D60: January | E60: 3503.035
A61: San Francisco | B61: 9 | D61: February | E61: 4138.205
A62: Toledo | B62: 9 | D62: March | E62: 4795.775
A63: Washington | B63: 26 | D63: April | E63: 4224.595
A64: Grand Total | B64: 174 | D64: May | E64: 3247.98
D65: June | E65: 4843.04
D66: July | E66: 3982.915
D67: August | E67: 2326.9
D68: September | E68: 3633.645
D69: October | E69: 3800.075
D70: November | E70: 3548.43
D71: December | E71: 3089.66
D72: Grand Total | E72: 45134.255
A75: Sum of Sales | B75: Column Labels
A76: Row Labels | B76: January | C76: February | D76: March | E76: April | F76: May | G76: June | H76: July | I76: August | J76: September | K76: October | L76: November | M76: December | N76: Grand Total
A77: Excelsa | B77: 677.72 | C77: 976.41 | D77: 1264.14 | E77: 1560.23 | F77: 970.33 | G77: 1598.195 | H77: 1141.555 | I77: 478.59 | J77: 771.085 | K77: 937.33 | L77: 771.38 | M77: 1159.475 | N77: 12306.44
A78: Grand Total | B78: 677.72 | C78: 976.41 | D78: 1264.14 | E78: 1560.23 | F78: 970.33 | G78: 1598.195 | H78: 1141.555 | I78: 478.59 | J78: 771.085 | K78: 937.33 | L78: 771.38 | M78: 1159.475 | N78: 12306.44
A83: Row Labels | B83: Count of CUSTOMER NAME
A84: January | B84: 91 | D84: Row Labels | E84: Sum of Sales
A85: February | B85: 95 | D85: 2019 | E85: 12187.165
A86: March | B86: 109 | D86: 2020 | E86: 12117.545
A87: April | B87: 86 | D87: 2021 | E87: 13766.11
A88: May | B88: 79 | D88: 2022 | E88: 7063.435
A89: June | B89: 88 | D89: Grand Total | E89: 45134.255
A90: July | B90: 91
A91: August | B91: 64 | M91: Sum of Sales
A92: September | B92: 73 | M92: 45134.255 | N92: =GETPIVOTDATA("Sales",$M$91) -> 45134.255
A93: October | B93: 85 | D93: Sum of Sales | E93: Column Labels
A94: November | B94: 68 | D94: Row Labels | E94: 2019 | F94: 2020 | G94: 2021 | H94: 2022 | I94: Grand Total
A95: December | B95: 71 | D95: Arabica | E95: 2926.63 | F95: 3356.415 | G95: 4045.63 | H95: 1439.82 | I95: 11768.495
A96: (blank) | D96: Dark | E96: 462.675 | F96: 907.44 | G96: 1290.515 | H96: 387.055 | I96: 3047.685
A97: Grand Total | B97: 1000 | D97: Light | E97: 1261.33 | F97: 1010.1 | G97: 1388.24 | H97: 572.39 | I97: 4232.06
D98: Medium | E98: 1202.625 | F98: 1438.875 | G98: 1366.875 | H98: 480.375 | I98: 4488.75
D99: Excelsa | E99: 3481.46 | F99: 3663.41 | G99: 3469.64 | H99: 1691.93 | I99: 12306.44
D100: Dark | E100: 578.34 | F100: 1329.21 | G100: 1194.345 | H100: 325.62 | I100: 3427.515
D101: Light | E101: 2104.245 | F101: 1069.2 | G101: 812.295 | H101: 810.81 | I101: 4796.55
D102: Medium | E102: 798.875 | F102: 1265 | G102: 1463 | H102: 555.5 | I102: 4082.375 | O102: Sum of PROFIT
D103: Liberica | E103: 3378.005 | F103: 2604.455 | G103: 3836.695 | H103: 2234.92 | I103: 12054.075 | O103: 1301.3751 | P103: =GETPIVOTDATA("PROFIT",$O$102) -> 1301.3751
D104: Dark | E104: 994.56 | F104: 1146.075 | G104: 1329.965 | H104: 625.485 | I104: 4096.085
D105: Light | E105: 1367.855 | F105: 963.68 | G105: 1363.1 | H105: 871.75 | I105: 4566.385 | L105: Count of CUSTOMER NAME
D106: Medium | E106: 1015.59 | F106: 494.7 | G106: 1143.63 | H106: 737.685 | I106: 3391.605 | L106: 1000 | M106: =GETPIVOTDATA("CUSTOMER NAME",$L$105) -> 1000
D107: Robusta | E107: 2401.07 | F107: 2493.265 | G107: 2414.145 | H107: 1696.765 | I107: 9005.245
D108: Dark | E108: 737.48 | F108: 604.125 | G108: 622.025 | H108: 644.4 | I108: 2608.03
D109: Light | E109: 891.47 | F109: 1228.46 | G109: 1100.595 | H109: 538.945 | I109: 3759.47
D110: Medium | E110: 772.12 | F110: 660.68 | G110: 691.525 | H110: 513.42 | I110: 2637.745 | O110: Sum of Quantity
D111: Grand Total | E111: 12187.165 | F111: 12117.545 | G111: 13766.11 | H111: 7063.435 | I111: 45134.255 | O111: 3551 | P111: =GETPIVOTDATA("Quantity",$O$110) -> 3551

Sheet DASHBOARD

Sheet WORKSHEET
A1: Order ID | B1: Order Date | C1: DAY | D1: MONTH | E1: YEAR | F1: Customer ID | G1: CUSTOMER NAME | H1: EMAIL | I1: PHONE NUMBER | J1: CITY | K1: COUNTRY | L1: LOYALTY CARD | M1: Product ID | N1: COFFEE TYPE | O1: ROAST TYPE | P1: PROFIT | Q1: Quantity | R1: Size | S1: Unit Price | T1: Sales | U1: TOTAL PROFIT | V1: PROFIT MARGINE
A2: QEV-37451-860 | B2: 43713 | C2: =TEXT(B2,"dddd") -> Thursday | D2: =TEXT(B2,"MMMM") -> September | E2: =TEXT(B2,"YYYY") -> 2019 | F2: 17670-51384-MA | G2: =VLOOKUP(F3,'Customers (2)'!A:I,2,0) -> Aloisia Allner | H2: =VLOOKUP(F2,'Customers (2)'!A:I,3,0) -> aallner0@lulu.com | I2: =VLOOKUP(F2,'Customers (2)'!A:I,4,0) -> +1 (862) 817-0124 | J2: =VLOOKUP(F2,'Customers (2)'!A:I,6,0) -> Paterson | K2: =VLOOKUP(F2,'Customers (2)'!A:I,7,0) -> United States | L2: =VLOOKUP(F2,'Customers (2)'!A:I,9,0) -> Yes | M2: R-M-1 | N2: =VLOOKUP(M2,'Products (2)'!A:G,2,0) -> Robusta | O2: =VLOOKUP(M2,'Products (2)'!A:G,3,0) -> Medium | P2: =VLOOKUP(M2,'Products (2)'!A:G,7,0) -> 0.597 | Q2: 2 | R2: =INDEX([1]products!$A$1:$G$49,MATCH([1]orders!$D2,[1]products!$A$1:$A$49,0),MATCH([1]orders!K$1,[1]products!$A$1:$G$1,0)) -> 1 | S2: =INDEX([1]products!$A$1:$G$49,MATCH([1]orders!$D2,[1]products!$A$1:$A$49,0),MATCH([1]orders!L$1,[1]products!$A$1:$G$1,0)) -> 9.95 | T2: =Q2*S2 -> 19.9 | U2: =Q2*P2 -> 1.194 | V2: =U2/T2*100 -> 6
A3: QEV-37451-860 | B3: 43713 | C3: =TEXT(B3,"dddd") -> Thursday | D3: =TEXT(B3,"MMMM") -> September | E3: =TEXT(B3,"YYYY") -> 2019 | F3: 17670-51384-MA | G3: =VLOOKUP(F4,'Customers (2)'!A:I,2,0) -> Jami Redholes | H3: =VLOOKUP(F3,'Customers (2)'!A:I,3,0) -> aallner0@lulu.com | I3: =VLOOKUP(F3,'Customers (2)'!A:I,4,0) -> +1 (862) 817-0124 | J3: =VLOOKUP(F3,'Customers (2)'!A:I,6,0) -> Paterson | K3: =VLOOKUP(F3,'Customers (2)'!A:I,7,0) -> United States | L3: =VLOOKUP(F3,'Customers (2)'!A:I,9,0) -> Yes | M3: E-M-0.5 | N3: =VLOOKUP(M3,'Products (2)'!A:G,2,0) -> Excelsa | O3: =VLOOKUP(M3,'Products (2)'!A:G,3,0) -> Medium | P3: =VLOOKUP(M3,'Products (2)'!A:G,7,0) -> 0.9075 | Q3: 5 | R3: =INDEX([1]products!$A$1:$G$49,MATCH([1]orders!$D3,[1]products!$A$1:$A$49,0),MATCH([1]orders!K$1,[1]products!$A$1:$G$1,0)) -> 0.5 | S3: =INDEX([1]products!$A$1:$G$49,MATCH([1]orders!$D3,[1]products!$A$1:$A$49,0),MATCH([1]orders!L$1,[1]products!$A$1:$G$1,0)) -> 8.25 | T3: =Q3*S3 -> 41.25 | U3: =Q3*P3 -> 4.5375 | V3: =U3/T3*100 -> 11
A4: FAA-43335-268 | B4: 44364 | C4: =TEXT(B4,"dddd") -> Thursday | D4: =TEXT(B4,"MMMM") -> June | E4: =TEXT(B4,"YYYY") -> 2021 | F4: 21125-22134-PX | G4: =VLOOKUP(F5,'Customers (2)'!A:I,2,0) -> Christoffer O' Shea | H4: =VLOOKUP(F4,'Customers (2)'!A:I,3,0) -> jredholes2@tmall.com | I4: =VLOOKUP(F4,'Customers (2)'!A:I,4,0) -> +1 (210) 986-6806 | J4: =VLOOKUP(F4,'Customers (2)'!A:I,6,0) -> San Antonio | K4: =VLOOKUP(F4,'Customers (2)'!A:I,7,0) -> United States | L4: =VLOOKUP(F4,'Customers (2)'!A:I,9,0) -> Yes | M4: A-L-1 | N4: =VLOOKUP(M4,'Products (2)'!A:G,2,0) -> Arabica | O4: =VLOOKUP(M4,'Products (2)'!A:G,3,0) -> Light | P4: =VLOOKUP(M4,'Products (2)'!A:G,7,0) -> 1.1655 | Q4: 1 | R4: =INDEX([1]products!$A$1:$G$49,MATCH([1]orders!$D4,[1]products!$A$1:$A$49,0),MATCH([1]orders!K$1,[1]products!$A$1:$G$1,0)) -> 1 | S4: =INDEX([1]products!$A$1:$G$49,MATCH([1]orders!$D4,[1]products!$A$1:$A$49,0),MATCH([1]orders!L$1,[1]products!$A$1:$G$1,0)) -> 12.95 | T4: =Q4*S4 -> 12.95 | U4: =Q4*P4 -> 1.1655 | V4: =U4/T4*100 -> 9
A5: KAC-83089-793 | B5: 44392 | C5: =TEXT(B5,"dddd") -> Thursday | D5: =TEXT(B5,"MMMM") -> July | E5: =TEXT(B5,"YYYY") -> 2021 | F5: 23806-46781-OU | G5: =VLOOKUP(F6,'Customers (2)'!A:I,2,0) -> Christoffer O' Shea | H5: =VLOOKUP(F5,'Customers (2)'!A:I,3,0) -> 0 | I5: =VLOOKUP(F5,'Customers (2)'!A:I,4,0) -> +353 (698) 362-9201 | J5: =VLOOKUP(F5,'Customers (2)'!A:I,6,0) -> Cill Airne | K5: =VLOOKUP(F5,'Customers (2)'!A:I,7,0) -> Ireland | L5: =VLOOKUP(F5,'Customers (2)'!A:I,9,0) -> No | M5: E-M-1 | N5: =VLOOKUP(M5,'Products (2)'!A:G,2,0) -> Excelsa | O5: =VLOOKUP(M5,'Products (2)'!A:G,3,0) -> Medium | P5: =VLOOKUP(M5,'Products (2)'!A:G,7,0) -> 1.5125 | Q5: 2 | R5: =INDEX([1]products!$A$1:$G$49,MATCH([1]orders!$D5,[1]products!$A$1:$A$49,0),MATCH([1]orders!K$1,[1]products!$A$1:$G$1,0)) -> 1 | S5: =INDEX([1]products!$A$1:$G$49,MATCH([1]orders!$D5,[1]products!$A$1:$A$49,0),MATCH([1]orders!L$1,[1]products!$A$1:$G$1,0)) -> 13.75 | T5: =Q5*S5 -> 27.5 | U5: =Q5*P5 -> 3.025 | V5: =U5/T5*100 -> 11
A6: KAC-83089-793 | B6: 44392 | C6: =TEXT(B6,"dddd") -> Thursday | D6: =TEXT(B6,"MMMM") -> July | E6: =TEXT(B6,"YYYY") -> 2021 | F6: 23806-46781-OU | G6: =VLOOKUP(F7,'Customers (2)'!A:I,2,0) -> Beryle Cottier | H6: =VLOOKUP(F6,'Customers (2)'!A:I,3,0) -> 0 | I6: =VLOOKUP(F6,'Customers (2)'!A:I,4,0) -> +353 (698) 362-9201 | J6: =VLOOKUP(F6,'Customers (2)'!A:I,6,0) -> Cill Airne | K6: =VLOOKUP(F6,'Customers (2)'!A:I,7,0) -> Ireland | L6: =VLOOKUP(F6,'Customers (2)'!A:I,9,0) -> No | M6: R-L-2.5 | N6: =VLOOKUP(M6,'Products (2)'!A:G,2,0) -> Robusta | O6: =VLOOKUP(M6,'Products (2)'!A:G,3,0) -> Light | P6: =VLOOKUP(M6,'Products (2)'!A:G,7,0) -> 1.6491 | Q6: 2 | R6: =INDEX([1]products!$A$1:$G$49,MATCH([1]orders!$D6,[1]products!$A$1:$A$49,0),MATCH([1]orders!K$1,[1]products!$A$1:$G$1,0)) -> 2.5 | S6: =INDEX([1]products!$A$1:$G$49,MATCH([1]orders!$D6,[1]products!$A$1:$A$49,0),MATCH([1]orders!L$1,[1]products!$A$1:$G$1,0)) -> 27.485 | T6: =Q6*S6 -> 54.97 | U6: =Q6*P6 -> 3.2982 | V6: =U6/T6*100 -> 6
A7: CVP-18956-553 | B7: 44412 | C7: =TEXT(B7,"dddd") -> Wednesday | D7: =TEXT(B7,"MMMM") -> August | E7: =TEXT(B7,"YYYY") -> 2021 | F7: 86561-91660-RB | G7: =VLOOKUP(F8,'Customers (2)'!A:I,2,0) -> Shaylynn Lobe | H7: =VLOOKUP(F7,'Customers (2)'!A:I,3,0) -> 0 | I7: =VLOOKUP(F7,'Customers (2)'!A:I,4,0) -> +1 (570) 289-7473 | J7: =VLOOKUP(F7,'Customers (2)'!A:I,6,0) -> Scranton | K7: =VLOOKUP(F7,'Customers (2)'!A:I,7,0) -> United States | L7: =VLOOKUP(F7,'Customers (2)'!A:I,9,0) -> No | M7: L-D-1 | N7: =VLOOKUP(M7,'Products (2)'!A:G,2,0) -> Liberica | O7: =VLOOKUP(M7,'Products (2)'!A:G,3,0) -> Dark | P7: =VLOOKUP(M7,'Products (2)'!A:G,7,0) -> 1.6835 | Q7: 3 | R7: =INDEX([1]products!$A$1:$G$49,MATCH([1]orders!$D7,[1]products!$A$1:$A$49,0),MATCH([1]orders!K$1,[1]products!$A$1:$G$1,0)) -> 1 | S7: =INDEX([1]products!$A$1:$G$49,MATCH([1]orders!$D7,[1]products!$A$1:$A$49,0),MATCH([1]orders!L$1,[1]products!$A$1:$G$1,0)) -> 12.95 | T7: =Q7*S7 -> 38.85 | U7: =Q7*P7 -> 5.0505 | V7: =U7/T7*100 -> 13
A8: IPP-31994-879 | B8: 44582 | C8: =TEXT(B8,"dddd") -> Friday | D8: =TEXT(B8,"MMMM") -> January | E8: =TEXT(B8,"YYYY") -> 2022 | F8: 65223-29612-CB | G8: =VLOOKUP(F9,'Customers (2)'!A:I,2,0) -> Melvin Wharfe | H8: =VLOOKUP(F8,'Customers (2)'!A:I,3,0) -> slobe6@nifty.com | I8: =VLOOKUP(F8,'Customers (2)'!A:I,4,0) -> +1 (937) 954-4541 | J8: =VLOOKUP(F8,'Customers (2)'!A:I,6,0) -> Dayton | K8: =VLOOKUP(F8,'Customers (2)'!A:I,7,0) -> United States | L8: =VLOOKUP(F8,'Customers (2)'!A:I,9,0) -> Yes | M8: E-D-0.5 | N8: =VLOOKUP(M8,'Products (2)'!A:G,2,0) -> Excelsa | O8: =VLOOKUP(M8,'Products (2)'!A:G,3,0) -> Dark | P8: =VLOOKUP(M8,'Products (2)'!A:G,7,0) -> 0.8019 | Q8: 3 | R8: =INDEX([1]products!$A$1:$G$49,MATCH([1]orders!$D8,[1]products!$A$1:$A$49,0),MATCH([1]orders!K$1,[1]products!$A$1:$G$1,0)) -> 0.5 | S8: =INDEX([1]products!$A$1:$G$49,MATCH([1]orders!$D8,[1]products!$A$1:$A$49,0),MATCH([1]orders!L$1,[1]products!$A$1:$G$1,0)) -> 7.29 | T8: =Q8*S8 -> 21.87 | U8: =Q8*P8 -> 2.4057 | V8: =U8/T8*100 -> 11
A9: SNZ-65340-705 | B9: 44701 | C9: =TEXT(B9,"dddd") -> Friday | D9: =TEXT(B9,"MMMM") -> May | E9: =TEXT(B9,"YYYY") -> 2022 | F9: 21134-81676-FR | G9: =VLOOKUP(F10,'Customers (2)'!A:I,2,0) -> Guthrey Petracci | H9: =VLOOKUP(F9,'Customers (2)'!A:I,3,0) -> 0 | I9: =VLOOKUP(F9,'Customers (2)'!A:I,4,0) -> +353 (507) 574-3034 | J9: =VLOOKUP(F9,'Customers (2)'!A:I,6,0) -> Kill | K9: =VLOOKUP(F9,'Customers (2)'!A:I,7,0) -> Ireland | L9: =VLOOKUP(F9,'Customers (2)'!A:I,9,0) -> Yes | M9: L-L-0.2 | N9: =VLOOKUP(M9,'Products (2)'!A:G,2,0) -> Liberica | O9: =VLOOKUP(M9,'Products (2)'!A:G,3,0) -> Light | P9: =VLOOKUP(M9,'Products (2)'!A:G,7,0) -> 0.61815 | Q9: 1 | R9: =INDEX([1]products!$A$1:$G$49,MATCH([1]orders!$D9,[1]products!$A$1:$A$49,0),MATCH([1]orders!K$1,[1]products!$A$1:$G$1,0)) -> 0.2 | S9: =INDEX([1]products!$A$1:$G$49,MATCH([1]orders!$D9,[1]products!$A$1:$A$49,0),MATCH([1]orders!L$1,[1]products!$A$1:$G$1,0)) -> 4.755 | T9: =Q9*S9 -> 4.755 | U9: =Q9*P9 -> 0.61815 | V9: =U9/T9*100 -> 13
A10: EZT-46571-659 | B10: 43467 | C10: =TEXT(B10,"dddd") -> Wednesday | D10: =TEXT(B10,"MMMM") -> January | E10: =TEXT(B10,"YYYY") -> 2019 | F10: 03396-68805-ZC | G10: =VLOOKUP(F11,'Customers (2)'!A:I,2,0) -> Rodger Raven | H10: =VLOOKUP(F10,'Customers (2)'!A:I,3,0) -> gpetracci8@livejournal.com | I10: =VLOOKUP(F10,'Customers (2)'!A:I,4,0) -> +1 (310) 868-1842 | J10: =VLOOKUP(F10,'Customers (2)'!A:I,6,0) -> Los Angeles | K10: =VLOOKUP(F10,'Customers (2)'!A:I,7,0) -> United States | L10: =VLOOKUP(F10,'Customers (2)'!A:I,9,0) -> No | M10: R-M-0.5 | N10: =VLOOKUP(M10,'Products (2)'!A:G,2,0) -> Robusta | O10: =VLOOKUP(M10,'Products (2)'!A:G,3,0) -> Medium | P10: =VLOOKUP(M10,'Products (2)'!A:G,7,0) -> 0.3582 | Q10: 3 | R10: =INDEX([1]products!$A$1:$G$49,MATCH([1]orders!$D10,[1]products!$A$1:$A$49,0),MATCH([1]orders!K$1,[1]products!$A$1:$G$1,0)) -> 0.5 | S10: =INDEX([1]products!$A$1:$G$49,MATCH([1]orders!$D10,[1]products!$A$1:$A$49,0),MATCH([1]orders!L$1,[1]products!$A$1:$G$1,0)) -> 5.97 | T10: =Q10*S10 -> 17.91 | U10: =Q10*P10 -> 1.0746 | V10: =U10/T10*100 -> 6
A11: NWQ-70061-912 | B11: 43713 | C11: =TEXT(B11,"dddd") -> Thursday | D11: =TEXT(B11,"MMMM") -> September | E11: =TEXT(B11,"YYYY") -> 2019 | F11: 61021-27840-ZN | G11: =VLOOKUP(F12,'Customers (2)'!A:I,2,0) -> Ferrell Ferber | H11: =VLOOKUP(F11,'Customers (2)'!A:I,3,0) -> rraven9@ed.gov | I11: =VLOOKUP(F11,'Customers (2)'!A:I,4,0) -> +1 (213) 263-0288 | J11: =VLOOKUP(F11,'Customers (2)'!A:I,6,0) -> Los Angeles | K11: =VLOOKUP(F11,'Customers (2)'!A:I,7,0) -> United States | L11: =VLOOKUP(F11,'Customers (2)'!A:I,9,0) -> No | M11: R-M-0.5 | N11: =VLOOKUP(M11,'Products (2)'!A:G,2,0) -> Robusta | O11: =VLOOKUP(M11,'Products (2)'!A:G,3,0) -> Medium | P11: =VLOOKUP(M11,'Products (2)'!A:G,7,0) -> 0.3582 | Q11: 1 | R11: =INDEX([1]products!$A$1:$G$49,MATCH([1]orders!$D11,[1]products!$A$1:$A$49,0),MATCH([1]orders!K$1,[1]products!$A$1:$G$1,0)) -> 0.5 | S11: =INDEX([1]products!$A$1:$G$49,MATCH([1]orders!$D11,[1]products!$A$1:$A$49,0),MATCH([1]orders!L$1,[1]products!$A$1:$G$1,0)) -> 5.97 | T11: =Q11*S11 -> 5.97 | U11: =Q11*P11 -> 0.3582 | V11: =U11/T11*100 -> 6
A12: BKK-47233-845 | B12: 44263 | C12: =TEXT(B12,"dddd") -> Monday | D12: =TEXT(B12,"MMMM") -> March | E12: =TEXT(B12,"YYYY") -> 2021 | F12: 76239-90137-UQ | G12: =VLOOKUP(F13,'Customers (2)'!A:I,2,0) -> Duky Phizackerly | H12: =VLOOKUP(F12,'Customers (2)'!A:I,3,0) -> fferbera@businesswire.com | I12: =VLOOKUP(F12,'Customers (2)'!A:I,4,0) -> +1 (408) 383-5302 | J12: =VLOOKUP(F12,'Customers (2)'!A:I,6,0) -> San Jose | K12: =VLOOKUP(F12,'Customers (2)'!A:I,7,0) -> United States | L12: =VLOOKUP(F12,'Customers (2)'!A:I,9,0) -> No | M12: A-D-1 | N12: =VLOOKUP(M12,'Products (2)'!A:G,2,0) -> Arabica | O12: =VLOOKUP(M12,'Products (2)'!A:G,3,0) -> Dark | P12: =VLOOKUP(M12,'Products (2)'!A:G,7,0) -> 0.8955 | Q12: 4 | R12: =INDEX([1]products!$A$1:$G$49,MATCH([1]orders!$D12,[1]products!$A$1:$A$49,0),MATCH([1]orders!K$1,[1]products!$A$1:$G$1,0)) -> 1 | S12: =INDEX([1]products!$A$1:$G$49,MATCH([1]orders!$D12,[1]products!$A$1:$A$49,0),MATCH([1]orders!L$1,[1]products!$A$1:$G$1,0)) -> 9.95 | T12: =Q12*S12 -> 39.8 | U12: =Q12*P12 -> 3.582 | V12: =U12/T12*100 -> 9
A13: VQR-01002-970 | B13: 44132 | C13: =TEXT(B13,"dddd") -> Wednesday | D13: =TEXT(B13,"MMMM") -> October | E13: =TEXT(B13,"YYYY") -> 2020 | F13: 49315-21985-BB | G13: =VLOOKUP(F14,'Customers (2)'!A:I,2,0) -> Rosaleen Scholar | H13: =VLOOKUP(F13,'Customers (2)'!A:I,3,0) -> dphizackerlyb@utexas.edu | I13: =VLOOKUP(F13,'Customers (2)'!A:I,4,0) -> +1 (408) 533-6012 | J13: =VLOOKUP(F13,'Customers (2)'!A:I,6,0) -> San Jose | K13: =VLOOKUP(F13,'Customers (2)'!A:I,7,0) -> United States | L13: =VLOOKUP(F13,'Customers (2)'!A:I,9,0) -> Yes | M13: E-L-2.5 | N13: =VLOOKUP(M13,'Products (2)'!A:G,2,0) -> Excelsa | O13: =VLOOKUP(M13,'Products (2)'!A:G,3,0) -> Light | P13: =VLOOKUP(M13,'Products (2)'!A:G,7,0) -> 3.75705 | Q13: 5 | R13: =INDEX([1]products!$A$1:$G$49,MATCH([1]orders!$D13,[1]products!$A$1:$A$49,0),MATCH([1]orders!K$1,[1]products!$A$1:$G$1,0)) -> 2.5 | S13: =INDEX([1]products!$A$1:$G$49,MATCH([1]orders!$D13,[1]products!$A$1:$A$49,0),MATCH([1]orders!L$1,[1]products!$A$1:$G$1,0)) -> 34.155 | T13: =Q13*S13 -> 170.775 | U13: =Q13*P13 -> 18.78525 | V13: =U13/T13*100 -> 11
... A1001: IRV-20769-219 | B1001: 44119 | C1001: =TEXT(B1001,"dddd") -> Thursday | D1001: =TEXT(B1001,"MMMM") -> October | E1001: =TEXT(B1001,"YYYY") -> 2020 | F1001: 77131-58092-GE | G1001: =VLOOKUP(F1002,'Customers (2)'!A:I,2,0) -> #N/A | H1001: =VLOOKUP(F1001,'Customers (2)'!A:I,3,0) -> 0 | I1001: =VLOOKUP(F1001,'Customers (2)'!A:I,4,0) -> +44 (810) 927-9266 | J1001: =VLOOKUP(F1001,'Customers (2)'!A:I,6,0) -> London | K1001: =VLOOKUP(F1001,'Customers (2)'!A:I,7,0) -> United Kingdom | L1001: =VLOOKUP(F1001,'Customers (2)'!A:I,9,0) -> Yes | M1001: E-M-0.2 | N1001: =VLOOKUP(M1001,'Products (2)'!A:G,2,0) -> Excelsa | O1001: =VLOOKUP(M1001,'Products (2)'!A:G,3,0) -> Medium | P1001: =VLOOKUP(M1001,'Products (2)'!A:G,7,0) -> 0.45375 | Q1001: 3 | R1001: =INDEX([1]products!$A$1:$G$49,MATCH([1]orders!$D1001,[1]products!$A$1:$A$49,0),MATCH([1]orders!K$1,[1]products!$A$1:$G$1,0)) -> 0.2 | S1001: =INDEX([1]products!$A$1:$G$49,MATCH([1]orders!$D1001,[1]products!$A$1:$A$49,0),MATCH([1]orders!L$1,[1]products!$A$1:$G$1,0)) -> 4.125 | T1001: =Q1001*S1001 -> 12.375 | U1001: =Q1001*P1001 -> 1.36125 | V1001: =U1001/T1001*100 -> 11
